camera_match/__init__.py
camera_match/metrics.py
camera_match/optimise.py
camera_match/pipeline.py
camera_match/preprocessing.py
camera_match/nodes/Curves.py
camera_match/nodes/LUT.py
camera_match/nodes/Matrix.py
camera_match/nodes/Node.py
camera_match/nodes/Transform.py
camera_match/nodes/__init__.py
camera_match/nodes/datasets/__init__.py
camera_match/nodes/datasets/emor.py
camera_match/nodes/tests/__init__.py
camera_match/nodes/tests/test_Curves.py
camera_match/nodes/tests/test_LUT.py
camera_match/nodes/tests/test_Matrix.py
camera_match/nodes/tests/test_Transform.py
camera_match/tests/__init__.py
camera_match/tests/test_pipeline.py
camera_match-0.1.0.dist-info/METADATA
camera_match-0.1.0.dist-info/WHEEL
camera_match-0.1.0.dist-info/licenses/LICENSE
camera_match-0.1.0.dist-info/RECORD
