Metadata-Version: 2.4
Name: camera-match
Version: 0.1.0
Summary: Match two cameras together using multiple algorithms
Project-URL: Homepage, https://github.com/ethan-ou/camera_match
Project-URL: Repository, https://github.com/ethan-ou/camera_match
Project-URL: Issues, https://github.com/ethan-ou/camera_match/issues
Author-email: Ethan Ou <ethantim@gmail.com>
License: MIT
License-File: LICENSE
Keywords: camera,camera_match,color,colour,grading
Classifier: Development Status :: 2 - Pre-Alpha
Classifier: Intended Audience :: Developers
Classifier: License :: OSI Approved :: MIT License
Classifier: Natural Language :: English
Classifier: Programming Language :: Python :: 3
Classifier: Programming Language :: Python :: 3.9
Classifier: Programming Language :: Python :: 3.10
Classifier: Programming Language :: Python :: 3.11
Classifier: Programming Language :: Python :: 3.12
Requires-Python: >=3.9
Requires-Dist: colour-science>=0.4.2
Requires-Dist: matplotlib
Requires-Dist: numpy
Requires-Dist: scipy
Provides-Extra: dev
Requires-Dist: pytest-cov>=5.0; extra == 'dev'
Requires-Dist: pytest-xdist>=3.0; extra == 'dev'
Requires-Dist: pytest>=8.0; extra == 'dev'
Requires-Dist: ruff>=0.4.0; extra == 'dev'
Requires-Dist: ty; extra == 'dev'
